{
  "materials": [
    {
      "item": {
        "tag": "forge:ingots/gold"
      },
      "count": 3
    },
    {
      "item": {
        "tag": "forge:ingots/iron"
      },
      "count": 5
    },
    {
      "item": {
        "tag": "minecraft:logs"
      },
      "count": 10
    },
    {
      "item": {
        "item": "pointblank:gunmetal_ingot"
      },
      "count": 18
    }, 
    {
      "item": {
        "item": "pointblank:guninternals"
      },
      "count": 6
    }
  ],
  "result": {
    "type": "gun",
    "id": "ww:i37"
  },
  "type": "tacz:gun_smith_table_crafting"
}