{
  "materials": [
    {
      "item": {
        "tag": "forge:ingots/iron"
      },
      "count": 9
    },
    {
      "item": {
        "item": "pointblank:gunmetal_ingot"
      },
      "count": 11
    }, 
    {
      "item": {
        "item": "pointblank:guninternals"
      },
      "count": 6
    },
    {
      "item": {
        "tag": "minecraft:logs"
      },
      "count": 12
    }
  ],
  "result": {
    "type": "gun",
    "id": "tacz:m870"
  },
  "type": "tacz:gun_smith_table_crafting"
}