{
  "materials": [
    {
      "item": {
        "tag": "forge:ingots/gold"
      },
      "count": 4
    },
    {
      "item": {
        "tag": "forge:ingots/iron"
      },
      "count": 11
    },
    {
      "item": {
        "item": "pointblank:gunmetal_ingot"
      },
      "count": 6
    }, 
    {
      "item": {
        "item": "pointblank:guninternals"
      },
      "count": 3
    },
    {
      "item": {
        "tag": "forge:gems/lapis"
      },
      "count": 2
    }
  ],
  "result": {
    "type": "gun",
    "id": "tacz:p320"
  },
  "type": "tacz:gun_smith_table_crafting"
}